[{"username":"kjakoubec0","password":"mN8!KJ","email":"zderdes0@seattletimes.com"},
{"username":"aflack1","password":"hR2?c","email":"erowth1@latimes.com"},
{"username":"tduke2","password":"lW4_4av","email":"ocanland2@mozilla.org"},
{"username":"mgosdin3","password":"yY8.p|Z.","email":"mclewlow3@hexun.com"},
{"username":"jjirik4","password":"sY8@a","email":"jblackhall4@hostgator.com"},
{"username":"alathwell5","password":"yU8\"bZ#|","email":"kgrieger5@mediafire.com"},
{"username":"vdat6","password":"mE7|","email":"sfernehough6@apple.com"},
{"username":"cmoralee7","password":"lR4/","email":"grouby7@cocolog-nifty.com"},
{"username":"nsummerell8","password":"zF1.","email":"pkidds8@fema.gov"},
{"username":"gcorrea9","password":"pD3&*","email":"acain9@hp.com"}]